{"items": [{"color": "Silver", "alt": "K1 88ahiwyu", "title": "Supreme\\xc2\\xae/Schott\\xc2\\xae Leather Work Jacket"}, {"color": "Black", "alt": "Gwm1jejzwdk", "title": "Supreme\\xc2\\xae/Schott\\xc2\\xae Leather Work Jacket"}, {"color": "Pale Red", "alt": "D4huaje9koo", "title": "Suede Varsity Jacket"}, {"color": "Royal", "alt": "Qyty7scvfwe", "title": "Suede Varsity Jacket"}, {"color": "Black", "alt": "Oo1v0choo5w", "title": "Suede Varsity Jacket"}, {"color": "Dark Purple", "alt": "4kqwu4rfhfa", "title": "Contrast Stitch Reversible MA-1 Jacket"}, {"color": "Acid Green", "alt": "0tuhondbtfo", "title": "Contrast Stitch Reversible MA-1 Jacket"}, {"color": "Black", "alt": "Iuah9t4ii8g", "title": "Contrast Stitch Reversible MA-1 Jacket"}, {"color": "Duck Brown", "alt": "3 69o1j3zoo", "title": "2-Tone Hooded Work Jacket "}, {"color": "Pink", "alt": "2eoqqb2zumu", "title": "2-Tone Hooded Work Jacket "}, {"color": "Black", "alt": "Cyywvasoaq8", "title": "2-Tone Hooded Work Jacket "}, {"color": "Red", "alt": "Pvw2il1dvme", "title": "Arc Logo Quilted Half Zip Pullover"}, {"color": "Black", "alt": "Hq7 r1fg qm", "title": "Arc Logo Quilted Half Zip Pullover"}, {"color": "Light Blue", "alt": "Rlv1bgw61vw", "title": "Arc Logo Quilted Half Zip Pullover"}, {"color": "Peach", "alt": "5dv2n2zedbm", "title": "Arc Logo Quilted Half Zip Pullover"}, {"color": "White", "alt": "Bvfwtsijbas", "title": "Arc Logo Quilted Half Zip Pullover"}, {"color": "Dusty Green", "alt": "Ivlvvzg2kei", "title": "Laces Rayon Shirt"}, {"color": "Black", "alt": "Oisujuxhijw", "title": "Laces Rayon Shirt"}, {"color": "Magenta", "alt": "Qjzc4j4qczo", "title": "Laces Rayon Shirt"}, {"color": "Rose", "alt": "Tyf39h7ipje", "title": "Faded Plaid Flannel Zip Up Shirt"}, {"color": "Navy", "alt": "7s7sx71mbr8", "title": "Faded Plaid Flannel Zip Up Shirt"}, {"color": "Moss", "alt": "Ecmgzumgpeq", "title": "Faded Plaid Flannel Zip Up Shirt"}, {"color": "Blue", "alt": "Qldusgvdirs", "title": "Printed Plaid Flannel Shirt"}, {"color": "Pink", "alt": "Kdfhmqsnzg8", "title": "Printed Plaid Flannel Shirt"}, {"color": "Grey", "alt": "Udiio8kp7 q", "title": "Printed Plaid Flannel Shirt"}, {"color": "Light Blue", "alt": "Hyor ly5rc8", "title": "Oxford Shirt"}, {"color": "Aqua/Light Blue Stripe", "alt": "Xq5utn4q8sm", "title": "Oxford Shirt"}, {"color": "Purple", "alt": "Ksou4wkvzi0", "title": "Oxford Shirt"}, {"color": "Red/Royal Stripe", "alt": "Czh2 sg0fd4", "title": "Oxford Shirt"}, {"color": "Peach", "alt": "Xmvh0ploxne", "title": "Oxford Shirt"}, {"color": "Green", "alt": "V8u icrgpwk", "title": "Oxford Shirt"}, {"color": "Tangerine", "alt": "Pm7fuyg0xjk", "title": "Sleeve Stripe Sweater"}, {"color": "Royal", "alt": "56f67gyw878", "title": "Sleeve Stripe Sweater"}, {"color": "Black", "alt": "Mgoredvjx0i", "title": "Sleeve Stripe Sweater"}, {"color": "Black", "alt": "Ew679cdteoo", "title": "Arrows Striped Polo Sweater"}, {"color": "Moss", "alt": "Cnd6kczml9c", "title": "Arrows Striped Polo Sweater"}, {"color": "Royal", "alt": "Wzhbwyq4iha", "title": "Arrows Striped Polo Sweater"}, {"color": "White", "alt": "Jyweiz6zy4i", "title": "Arrows Striped Polo Sweater"}, {"color": "Mint", "alt": "Jr4y15bkuva", "title": "Weave Knit Zip Up Polo"}, {"color": "Peach", "alt": "Hbvmnp vvgg", "title": "Weave Knit Zip Up Polo"}, {"color": "Black", "alt": "65txofn2nkk", "title": "Weave Knit Zip Up Polo"}, {"color": "Green", "alt": "Pilng6pyxio", "title": "Half Zip S/S Baseball Top"}, {"color": "Black", "alt": "Tg1k4jss84c", "title": "Half Zip S/S Baseball Top"}, {"color": "Yellow", "alt": "Hns4fuaxfe0", "title": "Half Zip S/S Baseball Top"}, {"color": "Navy", "alt": "Wdhmxh2ng6m", "title": "Contrast Hooded L/S Top"}, {"color": "Red", "alt": "9vg4ionz9ms", "title": "Contrast Hooded L/S Top"}, {"color": "Black", "alt": "2m g p45axa", "title": "Contrast Hooded L/S Top"}, {"color": "Gold", "alt": "Tkp rvpfa9s", "title": "Contrast Hooded L/S Top"}, {"color": "Purple", "alt": "E9oxiyny7da", "title": "Contrast Hooded L/S Top"}, {"color": "Magenta", "alt": "Namyp khw1s", "title": "Pique Logo L/S Top"}, {"color": "Acid Green", "alt": "Lnrt f26m e", "title": "Pique Logo L/S Top"}, {"color": "Orange", "alt": "V64pzgpz3pq", "title": "Pique Logo L/S Top"}, {"color": "White", "alt": "Zwrq6bvhxkg", "title": "Pique Logo L/S Top"}, {"color": "Black", "alt": "8ogvw i7ab4", "title": "Pique Logo L/S Top"}, {"color": "Navy", "alt": " y7wv cfgsw", "title": "Pique Logo L/S Top"}, {"color": "Navy", "alt": "Hilqx ytn3y", "title": "Overdyed Tee"}, {"color": "Brown", "alt": "Pxd oguinic", "title": "Overdyed Tee"}, {"color": "Pink", "alt": "5sq5qkg gfu", "title": "Overdyed Tee"}, {"color": "Gold", "alt": "A9duauhxg3i", "title": "Overdyed Tee"}, {"color": "White", "alt": "Ucz05zzdoky", "title": "Overdyed Tee"}, {"color": "Green", "alt": "Rncyg8n dee", "title": "Overdyed Tee"}, {"color": "Black", "alt": "Js zrxezvw0", "title": "Overdyed Tee"}, {"color": "White", "alt": "Qrvapaicf7i", "title": "Painted Flowers L/S Tee"}, {"color": "Slate", "alt": "Okrlhfeoqzo", "title": "Painted Flowers L/S Tee"}, {"color": "Gold", "alt": "4abhuf yqas", "title": "Painted Flowers L/S Tee"}, {"color": "Black", "alt": "R03gq5l imu", "title": "Painted Flowers L/S Tee"}, {"color": "White", "alt": "S bnqkfzti4", "title": "Chenille Arc Logo Hooded Sweatshirt"}, {"color": "Black", "alt": "Bkmpqg6uaho", "title": "Chenille Arc Logo Hooded Sweatshirt"}, {"color": "Heather Grey", "alt": "W4mhl5 zhxi", "title": "Chenille Arc Logo Hooded Sweatshirt"}, {"color": "Magenta", "alt": " czisfzr 8w", "title": "Chenille Arc Logo Hooded Sweatshirt"}, {"color": "Navy", "alt": "Qsgzsc3n9dm", "title": "Chenille Arc Logo Hooded Sweatshirt"}, {"color": "Pale Yellow", "alt": "Czxw9qktppy", "title": "Chenille Arc Logo Hooded Sweatshirt"}, {"color": "Red", "alt": "G7gvjjhgaei", "title": "Chenille Arc Logo Hooded Sweatshirt"}, {"color": "Sea Foam", "alt": "Npztu jpaik", "title": "Chenille Arc Logo Hooded Sweatshirt"}, {"color": "Black", "alt": "Xsugtetlwy0", "title": "Overdyed Hooded Sweatshirt"}, {"color": "Pink", "alt": "J0vxruylu7u", "title": "Overdyed Hooded Sweatshirt"}, {"color": "Gold", "alt": "9ubcrz4egag", "title": "Overdyed Hooded Sweatshirt"}, {"color": "Brown", "alt": "Hbhfhwkmmvm", "title": "Overdyed Hooded Sweatshirt"}, {"color": "Green", "alt": "Zxqm2pwirlq", "title": "Overdyed Hooded Sweatshirt"}, {"color": "Navy", "alt": "E8nkf1jpema", "title": "Overdyed Hooded Sweatshirt"}, {"color": "White", "alt": "Sko0rkvbmhc", "title": "Overdyed Hooded Sweatshirt"}, {"color": "Brown", "alt": "5kyb18jk7pu", "title": "Overdyed Crewneck"}, {"color": "Gold", "alt": "Vrqlnzcmmg4", "title": "Overdyed Crewneck"}, {"color": "Green", "alt": "Jgrmii7ycek", "title": "Overdyed Crewneck"}, {"color": "White", "alt": "L6ruzhsz0oq", "title": "Overdyed Crewneck"}, {"color": "Black", "alt": "Nlxpqyksxpg", "title": "Overdyed Crewneck"}, {"color": "Navy", "alt": "J3zzhr4c8ii", "title": "Overdyed Crewneck"}, {"color": "Pink", "alt": "Mdnsnila0vy", "title": "Overdyed Crewneck"}, {"color": "Magenta", "alt": "2alk a4pxzq", "title": "Laces Pant"}, {"color": "Black", "alt": "Cvemfh5s7cg", "title": "Laces Pant"}, {"color": "Dusty Green", "alt": "0yl9ygyaxqg", "title": "Laces Pant"}, {"color": "Khaki", "alt": "N4tgxmdtfzy", "title": "Work Pant"}, {"color": "Light Yellow", "alt": "Twekdxqxuzq", "title": "Work Pant"}, {"color": "Baby Blue", "alt": "Idttlpmyqi0", "title": "Work Pant"}, {"color": "Work Green", "alt": "Cg7t0vntfrm", "title": "Work Pant"}, {"color": "Pink", "alt": "W9jkzyhynoy", "title": "Work Pant"}, {"color": "Black", "alt": " 3pfnpoy 14", "title": "Work Pant"}, {"color": "Black/White", "alt": "Rf3xixy2heq", "title": "Work Pant"}, {"color": "Rust Brown", "alt": "Qmtat 5g1vk", "title": "Work Pant"}, {"color": "Light Navy", "alt": "1fcg287y mc", "title": "Work Pant"}, {"color": "White", "alt": "0gdghffvufe", "title": "Work Pant"}, {"color": "Light Coral", "alt": "Uz0iwicjsvk", "title": "Taped Seam Pant"}, {"color": "Black", "alt": "0f40nnpcov0", "title": "Taped Seam Pant"}, {"color": "Light Blue", "alt": "Zxawgwvgfba", "title": "Taped Seam Pant"}, {"color": "Navy", "alt": "V1nustw8uro", "title": "Multi Color Classic Logo Sweatpant"}, {"color": "Dusty Lavender", "alt": "Rtr7ci5zgje", "title": "Multi Color Classic Logo Sweatpant"}, {"color": "Black", "alt": "Ktqx5twq 9g", "title": "Multi Color Classic Logo Sweatpant"}, {"color": "Cardinal", "alt": "F8lx3fue8vq", "title": "Multi Color Classic Logo Sweatpant"}, {"color": "Heather Grey", "alt": "Kbgv8d0woja", "title": "Multi Color Classic Logo Sweatpant"}, {"color": "Moss", "alt": "Uck8vpvagw4", "title": "Multi Color Classic Logo Sweatpant"}, {"color": "White", "alt": "Xpm8qdrpuss", "title": "Multi Color Classic Logo Sweatpant"}, {"color": "Blue", "alt": "5ra1jsuarkc", "title": "Stone Washed Slim Jeans"}, {"color": "Black", "alt": "Dswwi1ljjti", "title": "Stone Washed Black Slim Jeans"}, {"color": "Indigo", "alt": "Ipmnzrl4jvk", "title": "Rigid Slim Jeans"}, {"color": "Washed Denim", "alt": "Jadtnjpvuzi", "title": "Washed Chino Twill Camp Cap"}, {"color": "Black", "alt": "6eyeoszatzk", "title": "Washed Chino Twill Camp Cap"}, {"color": "Pink", "alt": "3ngxjzjkw0a", "title": "Washed Chino Twill Camp Cap"}, {"color": "Red", "alt": "8vzxx6u45va", "title": "Washed Chino Twill Camp Cap"}, {"color": "Orange", "alt": "Qsfwjc rzlw", "title": "Washed Chino Twill Camp Cap"}, {"color": "Magenta", "alt": "Au191fbuwjo", "title": "Washed Chino Twill Camp Cap"}, {"color": "Navy", "alt": "E15adeamilq", "title": "Washed Chino Twill Camp Cap"}, {"color": "Sulphur", "alt": "Ykd1nao0yiq", "title": "Washed Chino Twill Camp Cap"}, {"color": "Yellow", "alt": "Tktfxc o05q", "title": "Tonal Vertical Logo 6-Panel"}, {"color": "Dark Green", "alt": "Bnt pixpl3e", "title": "Tonal Vertical Logo 6-Panel"}, {"color": "Purple", "alt": " 5nwlwqu3my", "title": "Tonal Vertical Logo 6-Panel"}, {"color": "Black", "alt": "Jxbl7phzhqe", "title": "Tonal Vertical Logo 6-Panel"}, {"color": "Red", "alt": "0ukveg1rfu0", "title": "Tonal Vertical Logo 6-Panel"}, {"color": "Navy", "alt": "Tcsi9tl vas", "title": "Tonal Vertical Logo 6-Panel"}, {"color": "Woodland Camo", "alt": "Qrd79krp85y", "title": "Script Logo 6-Panel"}, {"color": "Sulphur", "alt": "Bcenl6j53dm", "title": "Script Logo 6-Panel"}, {"color": "Pink", "alt": "6nq0wroq8vi", "title": "Script Logo 6-Panel"}, {"color": "Black", "alt": "Lt5lfg 0guq", "title": "Script Logo 6-Panel"}, {"color": "Navy", "alt": "Wmr ugn6s1k", "title": "Script Logo 6-Panel"}, {"color": "Orange", "alt": "Cxaqzxztpzq", "title": "Script Logo 6-Panel"}, {"color": "Red", "alt": "Rxngptewjku", "title": "Script Logo 6-Panel"}, {"color": "Orange", "alt": "Altpe2zz2gk", "title": "2-Tone Twill Top Panel Camp Cap"}, {"color": "Bright Royal", "alt": "C13mxo21zwy", "title": "2-Tone Twill Top Panel Camp Cap"}, {"color": "Magenta", "alt": "R3brou6bqyw", "title": "2-Tone Twill Top Panel Camp Cap"}, {"color": "Black", "alt": "I1la4ccpymm", "title": "2-Tone Twill Top Panel Camp Cap"}, {"color": "Red", "alt": "Jiechbsr1li", "title": "Go Fuck Yourself 5-Panel"}, {"color": "Brown", "alt": "Lkk6g2xykgk", "title": "Go Fuck Yourself 5-Panel"}, {"color": "Navy", "alt": "Uyvx72y1vf4", "title": "Go Fuck Yourself 5-Panel"}, {"color": "Black", "alt": "Kwxk38o5wzm", "title": "Go Fuck Yourself 5-Panel"}, {"color": "White", "alt": "Tx0dxvfavv4", "title": "Go Fuck Yourself 5-Panel"}, {"color": "Royal", "alt": "N49teg1vdxs", "title": "Warp 6-Panel"}, {"color": "Red", "alt": "Vzvjw5zmpty", "title": "Warp 6-Panel"}, {"color": "Black", "alt": "Ur5jddhurkg", "title": "Warp 6-Panel"}, {"color": "Brown", "alt": "Fbc6 na9vpk", "title": "Warp 6-Panel"}, {"color": "White", "alt": "8guc6ehag2w", "title": "Warp 6-Panel"}, {"color": "White", "alt": "Ewxinnjwxiw", "title": "Supreme\\xc2\\xae/Hanes\\xc2\\xae Tagless Tees (3 Pack)"}, {"color": "Black", "alt": "Skou kx eh8", "title": "Supreme\\xc2\\xae/Hanes\\xc2\\xae Tagless Tees (3 Pack)"}, {"color": "White", "alt": " xnycijyknu", "title": "Supreme\\xc2\\xae/Hanes\\xc2\\xae Boxer Briefs (4 Pack)"}, {"color": "Black", "alt": "Kqf8s49yi3k", "title": "Supreme\\xc2\\xae/Hanes\\xc2\\xae Boxer Briefs (4 Pack)"}, {"color": "White", "alt": "Mvyun4mi5ro", "title": "Supreme\\xc2\\xae/Hanes\\xc2\\xae Crew Socks (4 Pack)"}, {"color": "Black", "alt": "Aevrlaedquq", "title": "Supreme\\xc2\\xae/Hanes\\xc2\\xae Crew Socks (4 Pack)"}, {"color": "Gold", "alt": "Hrxmc ieulm", "title": "Gold Heart and Arrow Pendant"}, {"color": "Clear", "alt": "Ww1k6os5yco", "title": "Supreme\\xc2\\xae/Duralex\\xc2\\xae Glasses (Set of 4)"}, {"color": "Variety", "alt": "Iigurb fkbq", "title": "The Incense Match\\xe2\\x84\\xa2 Incense Matches (Pack of 3)"}, {"color": "Silver", "alt": "Bl3eco8dbti", "title": "Don't Be A Dick Pin"}, {"color": "Gold/Silver", "alt": "6ixqhvxgdfo", "title": "Oval Logo Keychain"}, {"color": "Red", "alt": "T1t7bvvkphq", "title": "666 Keychain"}, {"color": "Gold", "alt": "Hph2phclgvu", "title": "Supreme\\xc2\\xae/Vans\\xc2\\xae Velvet Leopard Sk8-Mid Pro"}, {"color": "Magenta", "alt": "6p6bbly z9a", "title": "Supreme\\xc2\\xae/Vans\\xc2\\xae Velvet Leopard Sk8-Mid Pro"}, {"color": "Royal", "alt": "Gkg20z yoey", "title": "Supreme\\xc2\\xae/Vans\\xc2\\xae Velvet Leopard Sk8-Mid Pro"}, {"color": "Black", "alt": "Q viwki3kr0", "title": "Supreme\\xc2\\xae/Vans\\xc2\\xae Velvet Leopard Sk8-Mid Pro"}, {"color": "Silver", "alt": "5vooay8vae8", "title": "Supreme\\xc2\\xae/Independent\\xc2\\xae Truck"}, {"color": "Red", "alt": "Skpdglskd s", "title": "Supreme\\xc2\\xae/Spitfire\\xc2\\xae Classic Wheels"}, {"color": "White", "alt": "Jpmcluycuq4", "title": "Supreme\\xc2\\xae/Spitfire\\xc2\\xae Classic Wheels"}, {"color": "Gold", "alt": "Qvj0uvw2o2e", "title": "Supreme\\xc2\\xae/Spitfire\\xc2\\xae Classic Wheels"}, {"color": "Black", "alt": "Ccfua3teed4", "title": "666 5-Pocket Jean"}, {"color": "Brown", "alt": "My98bcjbgfw", "title": "666 5-Pocket Jean"}, {"color": "Purple", "alt": "Gx8xcj 3nzs", "title": "Box Logo Piping New Era\\xc2\\xae "}, {"color": "Red", "alt": " qslkxrfr78", "title": "Box Logo Piping New Era\\xc2\\xae "}, {"color": "Black", "alt": "Jqk20qrjdvw", "title": "Box Logo Piping New Era\\xc2\\xae "}, {"color": "Green", "alt": "Xf82vjej2l0", "title": "Box Logo Piping New Era\\xc2\\xae "}, {"color": "Navy", "alt": "Yoqoteelbfq", "title": "Box Logo Piping New Era\\xc2\\xae "}, {"color": "Light Blue", "alt": "7cm dislkfs", "title": "Supreme\\xc2\\xae/Playboy\\xc2\\xae Pillbox"}, {"color": "Red", "alt": "F4tdhhaqmiq", "title": "Supreme\\xc2\\xae/Playboy\\xc2\\xae Pillbox"}, {"color": "White", "alt": "Giqz9soq7ry", "title": "Supreme\\xc2\\xae/Playboy\\xc2\\xae Pillbox"}, {"color": "Magenta", "alt": "Zzvgoo04gjg", "title": "Backpack"}, {"color": "Black", "alt": " 3gck8rz8rg", "title": "Backpack"}, {"color": "Acid Green", "alt": "Hct5yiou524", "title": "Backpack"}, {"color": "Teal", "alt": "Zf7pvpq2z8i", "title": "Backpack"}, {"color": "Black", "alt": "P4mq5unhqca", "title": "Supreme\\xc2\\xae/Vans\\xc2\\xae Velvet Leopard Sk8-Mid Pro"}]}